{
    "php-73": {
        "ca-central-1": 235,
        "eu-central-1": 235,
        "eu-north-1": 235,
        "eu-west-1": 235,
        "eu-west-2": 235,
        "eu-west-3": 235,
        "sa-east-1": 235,
        "us-east-1": 235,
        "us-east-2": 235,
        "us-west-1": 235,
        "us-west-2": 235,
        "ap-east-1": 131,
        "ap-south-1": 136,
        "ap-northeast-1": 135,
        "ap-northeast-2": 135,
        "ap-northeast-3": 131,
        "ap-southeast-1": 135,
        "ap-southeast-2": 135,
        "eu-south-1": 135,
        "eu-south-2": 24,
        "af-south-1": 55,
        "me-south-1": 49
    },
    "php-74": {
        "ca-central-1": 235,
        "eu-central-1": 235,
        "eu-north-1": 235,
        "eu-west-1": 235,
        "eu-west-2": 235,
        "eu-west-3": 235,
        "sa-east-1": 235,
        "us-east-1": 235,
        "us-east-2": 235,
        "us-west-1": 235,
        "us-west-2": 235,
        "ap-east-1": 131,
        "ap-south-1": 136,
        "ap-northeast-1": 135,
        "ap-northeast-2": 135,
        "ap-northeast-3": 131,
        "ap-southeast-1": 135,
        "ap-southeast-2": 135,
        "eu-south-1": 135,
        "eu-south-2": 24,
        "af-south-1": 55,
        "me-south-1": 49
    },
    "php-80": {
        "ca-central-1": 235,
        "eu-central-1": 235,
        "eu-north-1": 235,
        "eu-west-1": 235,
        "eu-west-2": 235,
        "eu-west-3": 235,
        "sa-east-1": 235,
        "us-east-1": 235,
        "us-east-2": 235,
        "us-west-1": 235,
        "us-west-2": 235,
        "ap-east-1": 131,
        "ap-south-1": 136,
        "ap-northeast-1": 135,
        "ap-northeast-2": 135,
        "ap-northeast-3": 131,
        "ap-southeast-1": 135,
        "ap-southeast-2": 135,
        "eu-south-1": 135,
        "eu-south-2": 24,
        "af-south-1": 55,
        "me-south-1": 49
    },
    "php-81": {
        "ca-central-1": 234,
        "eu-central-1": 234,
        "eu-north-1": 234,
        "eu-west-1": 234,
        "eu-west-2": 234,
        "eu-west-3": 234,
        "sa-east-1": 234,
        "us-east-1": 234,
        "us-east-2": 234,
        "us-west-1": 234,
        "us-west-2": 234,
        "ap-east-1": 131,
        "ap-south-1": 135,
        "ap-northeast-1": 135,
        "ap-northeast-2": 135,
        "ap-northeast-3": 131,
        "ap-southeast-1": 135,
        "ap-southeast-2": 135,
        "eu-south-1": 135,
        "eu-south-2": 24,
        "af-south-1": 55,
        "me-south-1": 49
    },
    "php-82": {
        "ca-central-1": 11,
        "eu-central-1": 11,
        "eu-north-1": 11,
        "eu-west-1": 11,
        "eu-west-2": 11,
        "eu-west-3": 11,
        "sa-east-1": 11,
        "us-east-1": 11,
        "us-east-2": 11,
        "us-west-1": 11,
        "us-west-2": 11,
        "ap-east-1": 11,
        "ap-south-1": 11,
        "ap-northeast-1": 11,
        "ap-northeast-2": 11,
        "ap-northeast-3": 11,
        "ap-southeast-1": 11,
        "ap-southeast-2": 11,
        "eu-south-1": 11,
        "eu-south-2": 11,
        "af-south-1": 11,
        "me-south-1": 11
    }
}